compaslib/__init__.py
compaslib-2019.11.26.data/scripts/compas2csv
compaslib-2019.11.26.dist-info/LICENSE.txt
compaslib-2019.11.26.dist-info/METADATA
compaslib-2019.11.26.dist-info/RECORD
compaslib-2019.11.26.dist-info/WHEEL
compaslib-2019.11.26.dist-info/top_level.txt
