Metadata-Version: 2.1
Name: compaslib
Version: 2019.11.26
Summary: A library to read/convert COMPAS ECG measurement files
Home-page: https://bitbucket.org/atpage/compaslib
Author: Alex Page
Author-email: alex.page@rochester.edu
License: MIT
Keywords: COMPAS ECG EKG
Platform: UNKNOWN
Requires-Dist: numpy
